{
  "schema_version": "1.1.0",
  "paper_id": "2308.06793",
  "module_name": "Paper_2308_06793",
  "grounding_policy": {
    "proof_countable": false,
    "claim_scope": "Paper-local symbol declarations ground notation for elaboration; they are not proofs of paper claims unless separately audited and Lean-verified."
  },
  "symbols": [
    {
      "latex": "L^2",
      "lean": "L2Space",
      "kind": "function_space",
      "declaration": "def L2Space : Set (ℝ → ℝ) := Set.univ",
      "grounding": "definition_stub",
      "reason": "l2_space_reference",
      "source": "seed_text",
      "grounding_kind": "mathlib_close_definition_stub",
      "grounding_source": "seed_text",
      "grounding_trust": "syntax_only_not_semantic_proof",
      "paper_agnostic_rule_id": "definition_stub.mathlib_close_match",
      "proof_countable": false
    },
    {
      "latex": "infty",
      "lean": "infty",
      "kind": "scalar",
      "declaration": "def infty : ℝ := 0",
      "grounding": "definition_stub",
      "reason": "infinity_symbol_placeholder",
      "source": "seed_text",
      "grounding_kind": "transparent_scalar_stub",
      "grounding_source": "seed_text",
      "grounding_trust": "syntax_only_not_semantic_proof",
      "paper_agnostic_rule_id": "definition_stub.scalar_parameter",
      "proof_countable": false
    },
    {
      "latex": "C",
      "lean": "C",
      "kind": "scalar",
      "declaration": "def C : ℝ := 0",
      "grounding": "definition_stub",
      "reason": "paper_scalar_or_distribution",
      "source": "seed_text",
      "grounding_kind": "transparent_scalar_stub",
      "grounding_source": "seed_text",
      "grounding_trust": "syntax_only_not_semantic_proof",
      "paper_agnostic_rule_id": "definition_stub.scalar_parameter",
      "proof_countable": false
    },
    {
      "latex": "a",
      "lean": "a",
      "kind": "scalar",
      "declaration": "def a : ℝ := 0",
      "grounding": "definition_stub",
      "reason": "paper_scalar_or_distribution",
      "source": "seed_text",
      "grounding_kind": "transparent_scalar_stub",
      "grounding_source": "seed_text",
      "grounding_trust": "syntax_only_not_semantic_proof",
      "paper_agnostic_rule_id": "definition_stub.scalar_parameter",
      "proof_countable": false
    },
    {
      "latex": "c_1",
      "lean": "c_1",
      "kind": "scalar",
      "declaration": "def c_1 : ℝ := 0",
      "grounding": "definition_stub",
      "reason": "paper_scalar_or_distribution",
      "source": "seed_text",
      "grounding_kind": "transparent_scalar_stub",
      "grounding_source": "seed_text",
      "grounding_trust": "syntax_only_not_semantic_proof",
      "paper_agnostic_rule_id": "definition_stub.scalar_parameter",
      "proof_countable": false
    },
    {
      "latex": "c_2",
      "lean": "c_2",
      "kind": "scalar",
      "declaration": "def c_2 : ℝ := 0",
      "grounding": "definition_stub",
      "reason": "paper_scalar_or_distribution",
      "source": "seed_text",
      "grounding_kind": "transparent_scalar_stub",
      "grounding_source": "seed_text",
      "grounding_trust": "syntax_only_not_semantic_proof",
      "paper_agnostic_rule_id": "definition_stub.scalar_parameter",
      "proof_countable": false
    },
    {
      "latex": "code1",
      "lean": "code1",
      "kind": "scalar",
      "declaration": "def code1 : ℝ := 0",
      "grounding": "definition_stub",
      "reason": "paper_scalar_or_distribution",
      "source": "seed_text",
      "grounding_kind": "transparent_scalar_stub",
      "grounding_source": "seed_text",
      "grounding_trust": "syntax_only_not_semantic_proof",
      "paper_agnostic_rule_id": "definition_stub.scalar_parameter",
      "proof_countable": false
    },
    {
      "latex": "code2",
      "lean": "code2",
      "kind": "scalar",
      "declaration": "def code2 : ℝ := 0",
      "grounding": "definition_stub",
      "reason": "paper_scalar_or_distribution",
      "source": "seed_text",
      "grounding_kind": "transparent_scalar_stub",
      "grounding_source": "seed_text",
      "grounding_trust": "syntax_only_not_semantic_proof",
      "paper_agnostic_rule_id": "definition_stub.scalar_parameter",
      "proof_countable": false
    },
    {
      "latex": "hemi2",
      "lean": "hemi2",
      "kind": "scalar",
      "declaration": "def hemi2 : ℝ := 0",
      "grounding": "definition_stub",
      "reason": "paper_scalar_or_distribution",
      "source": "seed_text",
      "grounding_kind": "transparent_scalar_stub",
      "grounding_source": "seed_text",
      "grounding_trust": "syntax_only_not_semantic_proof",
      "paper_agnostic_rule_id": "definition_stub.scalar_parameter",
      "proof_countable": false
    },
    {
      "latex": "partial_C",
      "lean": "partial_C",
      "kind": "scalar",
      "declaration": "def partial_C : ℝ := 0",
      "grounding": "definition_stub",
      "reason": "paper_scalar_or_distribution",
      "source": "seed_text",
      "grounding_kind": "transparent_scalar_stub",
      "grounding_source": "seed_text",
      "grounding_trust": "syntax_only_not_semantic_proof",
      "paper_agnostic_rule_id": "definition_stub.scalar_parameter",
      "proof_countable": false
    },
    {
      "latex": "perturb2",
      "lean": "perturb2",
      "kind": "scalar",
      "declaration": "def perturb2 : ℝ := 0",
      "grounding": "definition_stub",
      "reason": "paper_scalar_or_distribution",
      "source": "seed_text",
      "grounding_kind": "transparent_scalar_stub",
      "grounding_source": "seed_text",
      "grounding_trust": "syntax_only_not_semantic_proof",
      "paper_agnostic_rule_id": "definition_stub.scalar_parameter",
      "proof_countable": false
    },
    {
      "latex": "svjour3",
      "lean": "svjour3",
      "kind": "scalar",
      "declaration": "def svjour3 : ℝ := 0",
      "grounding": "definition_stub",
      "reason": "paper_scalar_or_distribution",
      "source": "seed_text",
      "grounding_kind": "transparent_scalar_stub",
      "grounding_source": "seed_text",
      "grounding_trust": "syntax_only_not_semantic_proof",
      "paper_agnostic_rule_id": "definition_stub.scalar_parameter",
      "proof_countable": false
    },
    {
      "latex": "theta",
      "lean": "theta",
      "kind": "scalar",
      "declaration": "def theta : ℝ := 0",
      "grounding": "definition_stub",
      "reason": "paper_scalar_or_distribution",
      "source": "seed_text",
      "grounding_kind": "transparent_scalar_stub",
      "grounding_source": "seed_text",
      "grounding_trust": "syntax_only_not_semantic_proof",
      "paper_agnostic_rule_id": "definition_stub.scalar_parameter",
      "proof_countable": false
    },
    {
      "latex": "varepsilon_1",
      "lean": "varepsilon_1",
      "kind": "scalar",
      "declaration": "def varepsilon_1 : ℝ := 0",
      "grounding": "definition_stub",
      "reason": "paper_scalar_or_distribution",
      "source": "seed_text",
      "grounding_kind": "transparent_scalar_stub",
      "grounding_source": "seed_text",
      "grounding_trust": "syntax_only_not_semantic_proof",
      "paper_agnostic_rule_id": "definition_stub.scalar_parameter",
      "proof_countable": false
    },
    {
      "latex": "varepsilon_2",
      "lean": "varepsilon_2",
      "kind": "scalar",
      "declaration": "def varepsilon_2 : ℝ := 0",
      "grounding": "definition_stub",
      "reason": "paper_scalar_or_distribution",
      "source": "seed_text",
      "grounding_kind": "transparent_scalar_stub",
      "grounding_source": "seed_text",
      "grounding_trust": "syntax_only_not_semantic_proof",
      "paper_agnostic_rule_id": "definition_stub.scalar_parameter",
      "proof_countable": false
    },
    {
      "latex": "varepsilon_3",
      "lean": "varepsilon_3",
      "kind": "scalar",
      "declaration": "def varepsilon_3 : ℝ := 0",
      "grounding": "definition_stub",
      "reason": "paper_scalar_or_distribution",
      "source": "seed_text",
      "grounding_kind": "transparent_scalar_stub",
      "grounding_source": "seed_text",
      "grounding_trust": "syntax_only_not_semantic_proof",
      "paper_agnostic_rule_id": "definition_stub.scalar_parameter",
      "proof_countable": false
    },
    {
      "latex": "partial_B",
      "lean": "partial_B",
      "kind": "scalar",
      "declaration": "def partial_B : ℝ := 0",
      "grounding": "definition_stub",
      "reason": "paper_scalar_or_distribution",
      "source": "latex_glossary",
      "grounding_kind": "transparent_scalar_stub",
      "grounding_source": "latex_glossary",
      "grounding_trust": "syntax_only_not_semantic_proof",
      "paper_agnostic_rule_id": "definition_stub.scalar_parameter",
      "proof_countable": false
    },
    {
      "latex": "h_R_x",
      "lean": "h_R_x",
      "kind": "scalar",
      "declaration": "def h_R_x : ℝ := 0",
      "grounding": "definition_stub",
      "reason": "paper_scalar_or_distribution",
      "source": "seed_text",
      "grounding_kind": "transparent_scalar_stub",
      "grounding_source": "seed_text",
      "grounding_trust": "syntax_only_not_semantic_proof",
      "paper_agnostic_rule_id": "definition_stub.scalar_parameter",
      "proof_countable": false
    },
    {
      "latex": "h1",
      "lean": "h1",
      "kind": "scalar",
      "declaration": "def h1 : ℝ := 0",
      "grounding": "definition_stub",
      "reason": "paper_scalar_or_distribution",
      "source": "seed_text",
      "grounding_kind": "transparent_scalar_stub",
      "grounding_source": "seed_text",
      "grounding_trust": "syntax_only_not_semantic_proof",
      "paper_agnostic_rule_id": "definition_stub.scalar_parameter",
      "proof_countable": false
    },
    {
      "latex": "h2",
      "lean": "h2",
      "kind": "scalar",
      "declaration": "def h2 : ℝ := 0",
      "grounding": "definition_stub",
      "reason": "paper_scalar_or_distribution",
      "source": "seed_text",
      "grounding_kind": "transparent_scalar_stub",
      "grounding_source": "seed_text",
      "grounding_trust": "syntax_only_not_semantic_proof",
      "paper_agnostic_rule_id": "definition_stub.scalar_parameter",
      "proof_countable": false
    },
    {
      "latex": "h_convex_polyhedral_second_order_1",
      "lean": "h_convex_polyhedral_second_order_1",
      "kind": "scalar",
      "declaration": "def h_convex_polyhedral_second_order_1 : ℝ := 0",
      "grounding": "definition_stub",
      "reason": "paper_scalar_or_distribution",
      "source": "seed_text",
      "grounding_kind": "transparent_scalar_stub",
      "grounding_source": "seed_text",
      "grounding_trust": "syntax_only_not_semantic_proof",
      "paper_agnostic_rule_id": "definition_stub.scalar_parameter",
      "proof_countable": false
    },
    {
      "latex": "h_pair_problem_2",
      "lean": "h_pair_problem_2",
      "kind": "scalar",
      "declaration": "def h_pair_problem_2 : ℝ := 0",
      "grounding": "definition_stub",
      "reason": "paper_scalar_or_distribution",
      "source": "seed_text",
      "grounding_kind": "transparent_scalar_stub",
      "grounding_source": "seed_text",
      "grounding_trust": "syntax_only_not_semantic_proof",
      "paper_agnostic_rule_id": "definition_stub.scalar_parameter",
      "proof_countable": false
    },
    {
      "latex": "h_source_3_3",
      "lean": "h_source_3_3",
      "kind": "scalar",
      "declaration": "def h_source_3_3 : ℝ := 0",
      "grounding": "definition_stub",
      "reason": "paper_scalar_or_distribution",
      "source": "seed_text",
      "grounding_kind": "transparent_scalar_stub",
      "grounding_source": "seed_text",
      "grounding_trust": "syntax_only_not_semantic_proof",
      "paper_agnostic_rule_id": "definition_stub.scalar_parameter",
      "proof_countable": false
    },
    {
      "latex": "c1",
      "lean": "c1",
      "kind": "scalar",
      "declaration": "def c1 : ℝ := 0",
      "grounding": "definition_stub",
      "reason": "paper_scalar_or_distribution",
      "source": "seed_text",
      "grounding_kind": "transparent_scalar_stub",
      "grounding_source": "seed_text",
      "grounding_trust": "syntax_only_not_semantic_proof",
      "paper_agnostic_rule_id": "definition_stub.scalar_parameter",
      "proof_countable": false
    },
    {
      "latex": "c2",
      "lean": "c2",
      "kind": "scalar",
      "declaration": "def c2 : ℝ := 0",
      "grounding": "definition_stub",
      "reason": "paper_scalar_or_distribution",
      "source": "seed_text",
      "grounding_kind": "transparent_scalar_stub",
      "grounding_source": "seed_text",
      "grounding_trust": "syntax_only_not_semantic_proof",
      "paper_agnostic_rule_id": "definition_stub.scalar_parameter",
      "proof_countable": false
    },
    {
      "latex": "hE_nonneg",
      "lean": "hE_nonneg",
      "kind": "scalar",
      "declaration": "def hE_nonneg : ℝ := 0",
      "grounding": "definition_stub",
      "reason": "paper_scalar_or_distribution",
      "source": "seed_text",
      "grounding_kind": "transparent_scalar_stub",
      "grounding_source": "seed_text",
      "grounding_trust": "syntax_only_not_semantic_proof",
      "paper_agnostic_rule_id": "definition_stub.scalar_parameter",
      "proof_countable": false
    },
    {
      "latex": "x0",
      "lean": "x0",
      "kind": "scalar",
      "declaration": "def x0 : ℝ := 0",
      "grounding": "definition_stub",
      "reason": "paper_scalar_or_distribution",
      "source": "seed_text",
      "grounding_kind": "transparent_scalar_stub",
      "grounding_source": "seed_text",
      "grounding_trust": "syntax_only_not_semantic_proof",
      "paper_agnostic_rule_id": "definition_stub.scalar_parameter",
      "proof_countable": false
    },
    {
      "latex": "y0",
      "lean": "y0",
      "kind": "scalar",
      "declaration": "def y0 : ℝ := 0",
      "grounding": "definition_stub",
      "reason": "paper_scalar_or_distribution",
      "source": "seed_text",
      "grounding_kind": "transparent_scalar_stub",
      "grounding_source": "seed_text",
      "grounding_trust": "syntax_only_not_semantic_proof",
      "paper_agnostic_rule_id": "definition_stub.scalar_parameter",
      "proof_countable": false
    },
    {
      "latex": "h_closed_W",
      "lean": "h_closed_W",
      "kind": "scalar",
      "declaration": "def h_closed_W : ℝ := 0",
      "grounding": "definition_stub",
      "reason": "paper_scalar_or_distribution",
      "source": "seed_text",
      "grounding_kind": "transparent_scalar_stub",
      "grounding_source": "seed_text",
      "grounding_trust": "syntax_only_not_semantic_proof",
      "paper_agnostic_rule_id": "definition_stub.scalar_parameter",
      "proof_countable": false
    },
    {
      "latex": "h_closed_Y",
      "lean": "h_closed_Y",
      "kind": "scalar",
      "declaration": "def h_closed_Y : ℝ := 0",
      "grounding": "definition_stub",
      "reason": "paper_scalar_or_distribution",
      "source": "seed_text",
      "grounding_kind": "transparent_scalar_stub",
      "grounding_source": "seed_text",
      "grounding_trust": "syntax_only_not_semantic_proof",
      "paper_agnostic_rule_id": "definition_stub.scalar_parameter",
      "proof_countable": false
    },
    {
      "latex": "h_convex_W",
      "lean": "h_convex_W",
      "kind": "scalar",
      "declaration": "def h_convex_W : ℝ := 0",
      "grounding": "definition_stub",
      "reason": "paper_scalar_or_distribution",
      "source": "seed_text",
      "grounding_kind": "transparent_scalar_stub",
      "grounding_source": "seed_text",
      "grounding_trust": "syntax_only_not_semantic_proof",
      "paper_agnostic_rule_id": "definition_stub.scalar_parameter",
      "proof_countable": false
    },
    {
      "latex": "l_rho_R_x_bar",
      "lean": "l_rho_R_x_bar",
      "kind": "scalar",
      "declaration": "def l_rho_R_x_bar : ℝ := 0",
      "grounding": "definition_stub",
      "reason": "paper_scalar_or_distribution",
      "source": "seed_text",
      "grounding_kind": "transparent_scalar_stub",
      "grounding_source": "seed_text",
      "grounding_trust": "syntax_only_not_semantic_proof",
      "paper_agnostic_rule_id": "definition_stub.scalar_parameter",
      "proof_countable": false
    },
    {
      "latex": "r_R_x_bar",
      "lean": "r_R_x_bar",
      "kind": "scalar",
      "declaration": "def r_R_x_bar : ℝ := 0",
      "grounding": "definition_stub",
      "reason": "paper_scalar_or_distribution",
      "source": "seed_text",
      "grounding_kind": "transparent_scalar_stub",
      "grounding_source": "seed_text",
      "grounding_trust": "syntax_only_not_semantic_proof",
      "paper_agnostic_rule_id": "definition_stub.scalar_parameter",
      "proof_countable": false
    },
    {
      "latex": "closed_W",
      "lean": "closed_W",
      "kind": "scalar",
      "declaration": "def closed_W : ℝ := 0",
      "grounding": "definition_stub",
      "reason": "paper_scalar_or_distribution",
      "source": "translation_schema",
      "grounding_kind": "transparent_scalar_stub",
      "grounding_source": "translation_schema",
      "grounding_trust": "syntax_only_not_semantic_proof",
      "paper_agnostic_rule_id": "definition_stub.scalar_parameter",
      "proof_countable": false
    },
    {
      "latex": "closed_Y",
      "lean": "closed_Y",
      "kind": "scalar",
      "declaration": "def closed_Y : ℝ := 0",
      "grounding": "definition_stub",
      "reason": "paper_scalar_or_distribution",
      "source": "translation_schema",
      "grounding_kind": "transparent_scalar_stub",
      "grounding_source": "translation_schema",
      "grounding_trust": "syntax_only_not_semantic_proof",
      "paper_agnostic_rule_id": "definition_stub.scalar_parameter",
      "proof_countable": false
    },
    {
      "latex": "convex_W",
      "lean": "convex_W",
      "kind": "scalar",
      "declaration": "def convex_W : ℝ := 0",
      "grounding": "definition_stub",
      "reason": "paper_scalar_or_distribution",
      "source": "translation_schema",
      "grounding_kind": "transparent_scalar_stub",
      "grounding_source": "translation_schema",
      "grounding_trust": "syntax_only_not_semantic_proof",
      "paper_agnostic_rule_id": "definition_stub.scalar_parameter",
      "proof_countable": false
    },
    {
      "latex": "h_newton_conv_gray_twice_1",
      "lean": "h_newton_conv_gray_twice_1",
      "kind": "scalar",
      "declaration": "def h_newton_conv_gray_twice_1 : ℝ := 0",
      "grounding": "definition_stub",
      "reason": "paper_scalar_or_distribution",
      "source": "seed_text",
      "grounding_kind": "transparent_scalar_stub",
      "grounding_source": "seed_text",
      "grounding_trust": "syntax_only_not_semantic_proof",
      "paper_agnostic_rule_id": "definition_stub.scalar_parameter",
      "proof_countable": false
    },
    {
      "latex": "h_pair_problem_problem_mani_2",
      "lean": "h_pair_problem_problem_mani_2",
      "kind": "scalar",
      "declaration": "def h_pair_problem_problem_mani_2 : ℝ := 0",
      "grounding": "definition_stub",
      "reason": "paper_scalar_or_distribution",
      "source": "seed_text",
      "grounding_kind": "transparent_scalar_stub",
      "grounding_source": "seed_text",
      "grounding_trust": "syntax_only_not_semantic_proof",
      "paper_agnostic_rule_id": "definition_stub.scalar_parameter",
      "proof_countable": false
    },
    {
      "latex": "h_residual_satisfies_stronger_estimate_5",
      "lean": "h_residual_satisfies_stronger_estimate_5",
      "kind": "scalar",
      "declaration": "def h_residual_satisfies_stronger_estimate_5 : ℝ := 0",
      "grounding": "definition_stub",
      "reason": "paper_scalar_or_distribution",
      "source": "seed_text",
      "grounding_kind": "transparent_scalar_stub",
      "grounding_source": "seed_text",
      "grounding_trust": "syntax_only_not_semantic_proof",
      "paper_agnostic_rule_id": "definition_stub.scalar_parameter",
      "proof_countable": false
    },
    {
      "latex": "h_sequence_generated_algorithm_rsqp_3",
      "lean": "h_sequence_generated_algorithm_rsqp_3",
      "kind": "scalar",
      "declaration": "def h_sequence_generated_algorithm_rsqp_3 : ℝ := 0",
      "grounding": "definition_stub",
      "reason": "paper_scalar_or_distribution",
      "source": "seed_text",
      "grounding_kind": "transparent_scalar_stub",
      "grounding_source": "seed_text",
      "grounding_trust": "syntax_only_not_semantic_proof",
      "paper_agnostic_rule_id": "definition_stub.scalar_parameter",
      "proof_countable": false
    },
    {
      "latex": "h_source_4_4",
      "lean": "h_source_4_4",
      "kind": "scalar",
      "declaration": "def h_source_4_4 : ℝ := 0",
      "grounding": "definition_stub",
      "reason": "paper_scalar_or_distribution",
      "source": "seed_text",
      "grounding_kind": "transparent_scalar_stub",
      "grounding_source": "seed_text",
      "grounding_trust": "syntax_only_not_semantic_proof",
      "paper_agnostic_rule_id": "definition_stub.scalar_parameter",
      "proof_countable": false
    },
    {
      "latex": "l_R_rho",
      "lean": "l_R_rho",
      "kind": "scalar",
      "declaration": "def l_R_rho : ℝ := 0",
      "grounding": "definition_stub",
      "reason": "paper_scalar_or_distribution",
      "source": "seed_text",
      "grounding_kind": "transparent_scalar_stub",
      "grounding_source": "seed_text",
      "grounding_trust": "syntax_only_not_semantic_proof",
      "paper_agnostic_rule_id": "definition_stub.scalar_parameter",
      "proof_countable": false
    },
    {
      "latex": "u_3",
      "lean": "u_3",
      "kind": "scalar",
      "declaration": "def u_3 : ℝ := 0",
      "grounding": "definition_stub",
      "reason": "paper_scalar_or_distribution",
      "source": "seed_text",
      "grounding_kind": "transparent_scalar_stub",
      "grounding_source": "seed_text",
      "grounding_trust": "syntax_only_not_semantic_proof",
      "paper_agnostic_rule_id": "definition_stub.scalar_parameter",
      "proof_countable": false
    },
    {
      "latex": "g_R_x",
      "lean": "g_R_x",
      "kind": "scalar",
      "declaration": "def g_R_x : ℝ := 0",
      "grounding": "definition_stub",
      "reason": "paper_scalar_or_distribution",
      "source": "seed_text",
      "grounding_kind": "transparent_scalar_stub",
      "grounding_source": "seed_text",
      "grounding_trust": "syntax_only_not_semantic_proof",
      "paper_agnostic_rule_id": "definition_stub.scalar_parameter",
      "proof_countable": false
    },
    {
      "latex": "hR_x",
      "lean": "hR_x",
      "kind": "scalar",
      "declaration": "def hR_x : ℝ := 0",
      "grounding": "definition_stub",
      "reason": "paper_scalar_or_distribution",
      "source": "seed_text",
      "grounding_kind": "transparent_scalar_stub",
      "grounding_source": "seed_text",
      "grounding_trust": "syntax_only_not_semantic_proof",
      "paper_agnostic_rule_id": "definition_stub.scalar_parameter",
      "proof_countable": false
    },
    {
      "latex": "l_R_x",
      "lean": "l_R_x",
      "kind": "scalar",
      "declaration": "def l_R_x : ℝ := 0",
      "grounding": "definition_stub",
      "reason": "paper_scalar_or_distribution",
      "source": "seed_text",
      "grounding_kind": "transparent_scalar_stub",
      "grounding_source": "seed_text",
      "grounding_trust": "syntax_only_not_semantic_proof",
      "paper_agnostic_rule_id": "definition_stub.scalar_parameter",
      "proof_countable": false
    },
    {
      "latex": "l_R_x_rho",
      "lean": "l_R_x_rho",
      "kind": "scalar",
      "declaration": "def l_R_x_rho : ℝ := 0",
      "grounding": "definition_stub",
      "reason": "paper_scalar_or_distribution",
      "source": "seed_text",
      "grounding_kind": "transparent_scalar_stub",
      "grounding_source": "seed_text",
      "grounding_trust": "syntax_only_not_semantic_proof",
      "paper_agnostic_rule_id": "definition_stub.scalar_parameter",
      "proof_countable": false
    },
    {
      "latex": "phi_R_x",
      "lean": "phi_R_x",
      "kind": "scalar",
      "declaration": "def phi_R_x : ℝ := 0",
      "grounding": "definition_stub",
      "reason": "paper_scalar_or_distribution",
      "source": "seed_text",
      "grounding_kind": "transparent_scalar_stub",
      "grounding_source": "seed_text",
      "grounding_trust": "syntax_only_not_semantic_proof",
      "paper_agnostic_rule_id": "definition_stub.scalar_parameter",
      "proof_countable": false
    },
    {
      "latex": "phi_R_x_rho",
      "lean": "phi_R_x_rho",
      "kind": "scalar",
      "declaration": "def phi_R_x_rho : ℝ := 0",
      "grounding": "definition_stub",
      "reason": "paper_scalar_or_distribution",
      "source": "seed_text",
      "grounding_kind": "transparent_scalar_stub",
      "grounding_source": "seed_text",
      "grounding_trust": "syntax_only_not_semantic_proof",
      "paper_agnostic_rule_id": "definition_stub.scalar_parameter",
      "proof_countable": false
    },
    {
      "latex": "l_R_x_",
      "lean": "l_R_x_",
      "kind": "scalar",
      "declaration": "def l_R_x_ : ℝ := 0",
      "grounding": "definition_stub",
      "reason": "paper_scalar_or_distribution",
      "source": "translation_schema",
      "grounding_kind": "transparent_scalar_stub",
      "grounding_source": "translation_schema",
      "grounding_trust": "syntax_only_not_semantic_proof",
      "paper_agnostic_rule_id": "definition_stub.scalar_parameter",
      "proof_countable": false
    },
    {
      "latex": "d_dt_C",
      "lean": "d_dt_C",
      "kind": "scalar",
      "declaration": "def d_dt_C : ℝ := 0",
      "grounding": "definition_stub",
      "reason": "paper_scalar_or_distribution",
      "source": "seed_text",
      "grounding_kind": "transparent_scalar_stub",
      "grounding_source": "seed_text",
      "grounding_trust": "syntax_only_not_semantic_proof",
      "paper_agnostic_rule_id": "definition_stub.scalar_parameter",
      "proof_countable": false
    },
    {
      "latex": "u_1",
      "lean": "u_1",
      "kind": "scalar",
      "declaration": "def u_1 : ℝ := 0",
      "grounding": "definition_stub",
      "reason": "paper_scalar_or_distribution",
      "source": "seed_text",
      "grounding_kind": "transparent_scalar_stub",
      "grounding_source": "seed_text",
      "grounding_trust": "syntax_only_not_semantic_proof",
      "paper_agnostic_rule_id": "definition_stub.scalar_parameter",
      "proof_countable": false
    },
    {
      "latex": "h_KKT",
      "lean": "h_KKT",
      "kind": "scalar",
      "declaration": "def h_KKT : ℝ := 0",
      "grounding": "definition_stub",
      "reason": "paper_scalar_or_distribution",
      "source": "translation_schema",
      "grounding_kind": "transparent_scalar_stub",
      "grounding_source": "translation_schema",
      "grounding_trust": "syntax_only_not_semantic_proof",
      "paper_agnostic_rule_id": "definition_stub.scalar_parameter",
      "proof_countable": false
    },
    {
      "latex": "h_M_RCQ",
      "lean": "h_M_RCQ",
      "kind": "scalar",
      "declaration": "def h_M_RCQ : ℝ := 0",
      "grounding": "definition_stub",
      "reason": "paper_scalar_or_distribution",
      "source": "translation_schema",
      "grounding_kind": "transparent_scalar_stub",
      "grounding_source": "translation_schema",
      "grounding_trust": "syntax_only_not_semantic_proof",
      "paper_agnostic_rule_id": "definition_stub.scalar_parameter",
      "proof_countable": false
    },
    {
      "latex": "z_0",
      "lean": "z_0",
      "kind": "scalar",
      "declaration": "def z_0 : ℝ := 0",
      "grounding": "definition_stub",
      "reason": "paper_scalar_or_distribution",
      "source": "seed_text",
      "grounding_kind": "transparent_scalar_stub",
      "grounding_source": "seed_text",
      "grounding_trust": "syntax_only_not_semantic_proof",
      "paper_agnostic_rule_id": "definition_stub.scalar_parameter",
      "proof_countable": false
    },
    {
      "latex": "h_manifold_strong_variational_sufficient_1",
      "lean": "h_manifold_strong_variational_sufficient_1",
      "kind": "scalar",
      "declaration": "def h_manifold_strong_variational_sufficient_1 : ℝ := 0",
      "grounding": "definition_stub",
      "reason": "paper_scalar_or_distribution",
      "source": "seed_text",
      "grounding_kind": "transparent_scalar_stub",
      "grounding_source": "seed_text",
      "grounding_trust": "syntax_only_not_semantic_proof",
      "paper_agnostic_rule_id": "definition_stub.scalar_parameter",
      "proof_countable": false
    },
    {
      "latex": "h_grad_some_5",
      "lean": "h_grad_some_5",
      "kind": "scalar",
      "declaration": "def h_grad_some_5 : ℝ := 0",
      "grounding": "definition_stub",
      "reason": "paper_scalar_or_distribution",
      "source": "seed_text",
      "grounding_kind": "transparent_scalar_stub",
      "grounding_source": "seed_text",
      "grounding_trust": "syntax_only_not_semantic_proof",
      "paper_agnostic_rule_id": "definition_stub.scalar_parameter",
      "proof_countable": false
    },
    {
      "latex": "h_manifold_strong_variational_sufficient_2",
      "lean": "h_manifold_strong_variational_sufficient_2",
      "kind": "scalar",
      "declaration": "def h_manifold_strong_variational_sufficient_2 : ℝ := 0",
      "grounding": "definition_stub",
      "reason": "paper_scalar_or_distribution",
      "source": "seed_text",
      "grounding_kind": "transparent_scalar_stub",
      "grounding_source": "seed_text",
      "grounding_trust": "syntax_only_not_semantic_proof",
      "paper_agnostic_rule_id": "definition_stub.scalar_parameter",
      "proof_countable": false
    },
    {
      "latex": "h_pair_problem_problem_mani_1",
      "lean": "h_pair_problem_problem_mani_1",
      "kind": "scalar",
      "declaration": "def h_pair_problem_problem_mani_1 : ℝ := 0",
      "grounding": "definition_stub",
      "reason": "paper_scalar_or_distribution",
      "source": "seed_text",
      "grounding_kind": "transparent_scalar_stub",
      "grounding_source": "seed_text",
      "grounding_trust": "syntax_only_not_semantic_proof",
      "paper_agnostic_rule_id": "definition_stub.scalar_parameter",
      "proof_countable": false
    },
    {
      "latex": "h_sequence_3",
      "lean": "h_sequence_3",
      "kind": "scalar",
      "declaration": "def h_sequence_3 : ℝ := 0",
      "grounding": "definition_stub",
      "reason": "paper_scalar_or_distribution",
      "source": "seed_text",
      "grounding_kind": "transparent_scalar_stub",
      "grounding_source": "seed_text",
      "grounding_trust": "syntax_only_not_semantic_proof",
      "paper_agnostic_rule_id": "definition_stub.scalar_parameter",
      "proof_countable": false
    },
    {
      "latex": "h_W_closed",
      "lean": "h_W_closed",
      "kind": "scalar",
      "declaration": "def h_W_closed : ℝ := 0",
      "grounding": "definition_stub",
      "reason": "paper_scalar_or_distribution",
      "source": "seed_text",
      "grounding_kind": "transparent_scalar_stub",
      "grounding_source": "seed_text",
      "grounding_trust": "syntax_only_not_semantic_proof",
      "paper_agnostic_rule_id": "definition_stub.scalar_parameter",
      "proof_countable": false
    },
    {
      "latex": "h_W_convex",
      "lean": "h_W_convex",
      "kind": "scalar",
      "declaration": "def h_W_convex : ℝ := 0",
      "grounding": "definition_stub",
      "reason": "paper_scalar_or_distribution",
      "source": "seed_text",
      "grounding_kind": "transparent_scalar_stub",
      "grounding_source": "seed_text",
      "grounding_trust": "syntax_only_not_semantic_proof",
      "paper_agnostic_rule_id": "definition_stub.scalar_parameter",
      "proof_countable": false
    },
    {
      "latex": "h_Y_closed",
      "lean": "h_Y_closed",
      "kind": "scalar",
      "declaration": "def h_Y_closed : ℝ := 0",
      "grounding": "definition_stub",
      "reason": "paper_scalar_or_distribution",
      "source": "seed_text",
      "grounding_kind": "transparent_scalar_stub",
      "grounding_source": "seed_text",
      "grounding_trust": "syntax_only_not_semantic_proof",
      "paper_agnostic_rule_id": "definition_stub.scalar_parameter",
      "proof_countable": false
    },
    {
      "latex": "h_Y_convex",
      "lean": "h_Y_convex",
      "kind": "scalar",
      "declaration": "def h_Y_convex : ℝ := 0",
      "grounding": "definition_stub",
      "reason": "paper_scalar_or_distribution",
      "source": "seed_text",
      "grounding_kind": "transparent_scalar_stub",
      "grounding_source": "seed_text",
      "grounding_trust": "syntax_only_not_semantic_proof",
      "paper_agnostic_rule_id": "definition_stub.scalar_parameter",
      "proof_countable": false
    },
    {
      "latex": "h_Z_def",
      "lean": "h_Z_def",
      "kind": "scalar",
      "declaration": "def h_Z_def : ℝ := 0",
      "grounding": "definition_stub",
      "reason": "paper_scalar_or_distribution",
      "source": "translation_schema",
      "grounding_kind": "transparent_scalar_stub",
      "grounding_source": "translation_schema",
      "grounding_trust": "syntax_only_not_semantic_proof",
      "paper_agnostic_rule_id": "definition_stub.scalar_parameter",
      "proof_countable": false
    },
    {
      "latex": "h_ball_subset_Y",
      "lean": "h_ball_subset_Y",
      "kind": "scalar",
      "declaration": "def h_ball_subset_Y : ℝ := 0",
      "grounding": "definition_stub",
      "reason": "paper_scalar_or_distribution",
      "source": "translation_schema",
      "grounding_kind": "transparent_scalar_stub",
      "grounding_source": "translation_schema",
      "grounding_trust": "syntax_only_not_semantic_proof",
      "paper_agnostic_rule_id": "definition_stub.scalar_parameter",
      "proof_countable": false
    },
    {
      "latex": "l_R_x_bar",
      "lean": "l_R_x_bar",
      "kind": "scalar",
      "declaration": "def l_R_x_bar : ℝ := 0",
      "grounding": "definition_stub",
      "reason": "paper_scalar_or_distribution",
      "source": "translation_schema",
      "grounding_kind": "transparent_scalar_stub",
      "grounding_source": "translation_schema",
      "grounding_trust": "syntax_only_not_semantic_proof",
      "paper_agnostic_rule_id": "definition_stub.scalar_parameter",
      "proof_countable": false
    },
    {
      "latex": "h_satisfies_condition_first_mani_1",
      "lean": "h_satisfies_condition_first_mani_1",
      "kind": "scalar",
      "declaration": "def h_satisfies_condition_first_mani_1 : ℝ := 0",
      "grounding": "definition_stub",
      "reason": "paper_scalar_or_distribution",
      "source": "seed_text",
      "grounding_kind": "transparent_scalar_stub",
      "grounding_source": "seed_text",
      "grounding_trust": "syntax_only_not_semantic_proof",
      "paper_agnostic_rule_id": "definition_stub.scalar_parameter",
      "proof_countable": false
    },
    {
      "latex": "poly_delta_hemi2",
      "lean": "poly_delta_hemi2",
      "kind": "scalar",
      "declaration": "def poly_delta_hemi2 : ℝ := 0",
      "grounding": "definition_stub",
      "reason": "paper_scalar_or_distribution",
      "source": "seed_text",
      "grounding_kind": "transparent_scalar_stub",
      "grounding_source": "seed_text",
      "grounding_trust": "syntax_only_not_semantic_proof",
      "paper_agnostic_rule_id": "definition_stub.scalar_parameter",
      "proof_countable": false
    },
    {
      "latex": "grad_x_l_R_rho",
      "lean": "grad_x_l_R_rho",
      "kind": "scalar",
      "declaration": "def grad_x_l_R_rho : ℝ := 0",
      "grounding": "definition_stub",
      "reason": "paper_scalar_or_distribution",
      "source": "seed_text",
      "grounding_kind": "transparent_scalar_stub",
      "grounding_source": "seed_text",
      "grounding_trust": "syntax_only_not_semantic_proof",
      "paper_agnostic_rule_id": "definition_stub.scalar_parameter",
      "proof_countable": false
    },
    {
      "latex": "partial_grad_x_l_R_rho",
      "lean": "partial_grad_x_l_R_rho",
      "kind": "scalar",
      "declaration": "def partial_grad_x_l_R_rho : ℝ := 0",
      "grounding": "definition_stub",
      "reason": "paper_scalar_or_distribution",
      "source": "seed_text",
      "grounding_kind": "transparent_scalar_stub",
      "grounding_source": "seed_text",
      "grounding_trust": "syntax_only_not_semantic_proof",
      "paper_agnostic_rule_id": "definition_stub.scalar_parameter",
      "proof_countable": false
    }
  ]
}