{"nodes": [{"id": "build_tc_graph_phase1", "label": "Mathlib TC Hierarchy Parser (Phase 1)", "file_type": "code", "source_file": "scripts/build_tc_graph.py", "source_location": "line 1", "source_url": null, "captured_at": null, "author": null, "contributor": null}], "edges": [{"source": "build_tc_graph_phase1", "target": "statement_translator_load_tc_graph", "relation": "shares_data_with", "confidence": "EXTRACTED", "confidence_score": 1.0, "source_file": "scripts/build_tc_graph.py", "source_location": "line 11", "weight": 1.0}], "hyperedges": []}